{
  "openapi": "3.0.1",
  "info": {
    "title": "api",
    "version": "v1"
  },
  "paths": {
    "/api/apartment": {
      "get": {
        "tags": [
          "apartment"
        ],
        "responses": {
          "200": {
            "description": "OK",
            "content": {
              "text/plain": {
                "schema": {
                  "type": "array",
                  "items": {
                    "$ref": "#/components/schemas/apartment"
                  }
                }
              },
              "application/json": {
                "schema": {
                  "type": "array",
                  "items": {
                    "$ref": "#/components/schemas/apartment"
                  }
                }
              },
              "text/json": {
                "schema": {
                  "type": "array",
                  "items": {
                    "$ref": "#/components/schemas/apartment"
                  }
                }
              }
            }
          }
        }
      }
    },
    "/api/apartment/getById/{id}": {
      "get": {
        "tags": [
          "apartment"
        ],
        "parameters": [
          {
            "name": "id",
            "in": "path",
            "required": true,
            "schema": {
              "type": "string"
            }
          }
        ],
        "responses": {
          "200": {
            "description": "OK"
          }
        }
      }
    },
    "/api/apartment/deleteById/{id}": {
      "delete": {
        "tags": [
          "apartment"
        ],
        "parameters": [
          {
            "name": "id",
            "in": "path",
            "required": true,
            "schema": {
              "type": "string"
            }
          }
        ],
        "responses": {
          "200": {
            "description": "OK"
          }
        }
      }
    },
    "/api/apartment/insertById": {
      "post": {
        "tags": [
          "apartment"
        ],
        "requestBody": {
          "content": {
            "application/json": {
              "schema": {
                "$ref": "#/components/schemas/apartment"
              }
            },
            "text/json": {
              "schema": {
                "$ref": "#/components/schemas/apartment"
              }
            },
            "application/*+json": {
              "schema": {
                "$ref": "#/components/schemas/apartment"
              }
            }
          }
        },
        "responses": {
          "200": {
            "description": "OK"
          }
        }
      }
    },
    "/api/apartment/updateById/{id}": {
      "put": {
        "tags": [
          "apartment"
        ],
        "parameters": [
          {
            "name": "id",
            "in": "path",
            "required": true,
            "schema": {
              "type": "string"
            }
          }
        ],
        "requestBody": {
          "content": {
            "application/json": {
              "schema": {
                "$ref": "#/components/schemas/apartment"
              }
            },
            "text/json": {
              "schema": {
                "$ref": "#/components/schemas/apartment"
              }
            },
            "application/*+json": {
              "schema": {
                "$ref": "#/components/schemas/apartment"
              }
            }
          }
        },
        "responses": {
          "200": {
            "description": "OK"
          }
        }
      }
    },
    "/api/Customers": {
      "get": {
        "tags": [
          "Customers"
        ],
        "responses": {
          "200": {
            "description": "OK",
            "content": {
              "text/plain": {
                "schema": {
                  "type": "array",
                  "items": {
                    "$ref": "#/components/schemas/customer"
                  }
                }
              },
              "application/json": {
                "schema": {
                  "type": "array",
                  "items": {
                    "$ref": "#/components/schemas/customer"
                  }
                }
              },
              "text/json": {
                "schema": {
                  "type": "array",
                  "items": {
                    "$ref": "#/components/schemas/customer"
                  }
                }
              }
            }
          }
        }
      }
    },
    "/api/Customers/getById/{id}": {
      "get": {
        "tags": [
          "Customers"
        ],
        "parameters": [
          {
            "name": "id",
            "in": "path",
            "required": true,
            "schema": {
              "type": "string"
            }
          }
        ],
        "responses": {
          "200": {
            "description": "OK"
          }
        }
      }
    },
    "/api/Customers/deleteById/{id}": {
      "delete": {
        "tags": [
          "Customers"
        ],
        "parameters": [
          {
            "name": "id",
            "in": "path",
            "required": true,
            "schema": {
              "type": "string"
            }
          }
        ],
        "responses": {
          "200": {
            "description": "OK"
          }
        }
      }
    },
    "/api/Customers/insertById": {
      "post": {
        "tags": [
          "Customers"
        ],
        "requestBody": {
          "content": {
            "application/json": {
              "schema": {
                "$ref": "#/components/schemas/customer"
              }
            },
            "text/json": {
              "schema": {
                "$ref": "#/components/schemas/customer"
              }
            },
            "application/*+json": {
              "schema": {
                "$ref": "#/components/schemas/customer"
              }
            }
          }
        },
        "responses": {
          "200": {
            "description": "OK"
          }
        }
      }
    },
    "/api/Customers/updateById/{id}": {
      "put": {
        "tags": [
          "Customers"
        ],
        "parameters": [
          {
            "name": "id",
            "in": "path",
            "required": true,
            "schema": {
              "type": "string"
            }
          }
        ],
        "requestBody": {
          "content": {
            "application/json": {
              "schema": {
                "$ref": "#/components/schemas/customer"
              }
            },
            "text/json": {
              "schema": {
                "$ref": "#/components/schemas/customer"
              }
            },
            "application/*+json": {
              "schema": {
                "$ref": "#/components/schemas/customer"
              }
            }
          }
        },
        "responses": {
          "200": {
            "description": "OK"
          }
        }
      }
    },
    "/api/Function/send": {
      "get": {
        "tags": [
          "Function"
        ],
        "responses": {
          "200": {
            "description": "OK"
          }
        }
      }
    }
  },
  "components": {
    "schemas": {
      "apartment": {
        "type": "object",
        "properties": {
          "id": {
            "type": "string",
            "nullable": true
          },
          "type": {
            "type": "string",
            "nullable": true
          },
          "titlenumber_room": {
            "type": "string",
            "nullable": true
          },
          "city": {
            "type": "string",
            "nullable": true
          },
          "neighborhoodMeter": {
            "type": "string",
            "nullable": true
          },
          "price": {
            "type": "number",
            "format": "double"
          },
          "rooms": {
            "type": "number",
            "format": "double"
          },
          "bathrooms": {
            "type": "integer",
            "format": "int32"
          },
          "size": {
            "type": "integer",
            "format": "int32"
          },
          "image": {
            "type": "string",
            "nullable": true
          },
          "floor": {
            "type": "integer",
            "format": "int32"
          },
          "features": {
            "type": "array",
            "items": {
              "type": "string"
            },
            "nullable": true
          }
        },
        "additionalProperties": false
      },
      "customer": {
        "type": "object",
        "properties": {
          "id": {
            "type": "string",
            "nullable": true
          },
          "title": {
            "type": "string",
            "nullable": true
          },
          "expert": {
            "type": "string",
            "nullable": true
          },
          "name": {
            "type": "string",
            "nullable": true
          }
        },
        "additionalProperties": false
      }
    }
  }
}